content_disposition/__init__.py
content_disposition/content_disposition.py
content_disposition-1.2.0.dist-info/LICENSE
content_disposition-1.2.0.dist-info/METADATA
content_disposition-1.2.0.dist-info/WHEEL
content_disposition-1.2.0.dist-info/top_level.txt
content_disposition-1.2.0.dist-info/RECORD
