Metadata-Version: 2.1
Name: content-disposition
Version: 1.2.0
Summary: A library that allows easy management of "Content-Disposition" details of HTTP responses.
Home-page: https://github.com/anexia/python-content-disposition
Author: Alexandra Bruckner
Author-email: abruckner@anexia-it.com
License: MIT License
Platform: UNKNOWN
Classifier: Development Status :: 5 - Production/Stable
Classifier: Intended Audience :: Developers
Classifier: License :: OSI Approved :: MIT License
Classifier: Operating System :: OS Independent
Classifier: Programming Language :: Python
Classifier: Programming Language :: Python :: 3
Classifier: Programming Language :: Python :: 3.9
Classifier: Programming Language :: Python :: 3.10
Classifier: Programming Language :: Python :: 3.11
Classifier: Programming Language :: Python :: 3.12
Classifier: Programming Language :: Python :: 3.13
License-File: LICENSE
